admin_global_search/__init__.py
admin_global_search/admin.py
admin_global_search/apps.py
admin_global_search/migrations/__init__.py
admin_global_search/models.py
admin_global_search/templates/admin/base_site.html
admin_global_search/templates/admin_global_search/results.html
admin_global_search/tests.py
admin_global_search/views.py
django_admin_global_search-0.0.6.dist-info/METADATA
django_admin_global_search-0.0.6.dist-info/WHEEL
django_admin_global_search-0.0.6.dist-info/licenses/LICENSE
django_admin_global_search-0.0.6.dist-info/RECORD
