Metadata-Version: 2.4
Name: django-admin-global-search
Version: 0.0.6
Summary: A global search for Django Admin UI
License: BSD 3-Clause License
License-File: LICENSE
Keywords: django,admin,global,search
Author: Stanislav Filin
Author-email: stasfilin@hotmail.com
Requires-Python: >=3.8,<4.0
Classifier: Development Status :: 4 - Beta
Classifier: Framework :: Django
Classifier: License :: OSI Approved :: BSD License
Classifier: License :: Other/Proprietary License
Classifier: Operating System :: OS Independent
Classifier: Programming Language :: Python :: 3
Classifier: Programming Language :: Python :: 3.8
Classifier: Programming Language :: Python :: 3.9
Classifier: Programming Language :: Python :: 3.10
Classifier: Programming Language :: Python :: 3.11
Classifier: Programming Language :: Python :: 3.12
Classifier: Programming Language :: Python :: 3.13
Classifier: Programming Language :: Python :: 3.14
Classifier: Topic :: Software Development :: Libraries :: Python Modules
Requires-Dist: django (>=4.2.26,<5.0.0) ; python_version < "3.10"
Requires-Dist: django (>=5.1.14,<5.2.0) ; python_version >= "3.10"
Project-URL: Bug Tracker, https://github.com/stasfilin/django-admin-global-search/issues
Project-URL: Homepage, https://github.com/stasfilin/django-admin-global-search
Project-URL: Repository, https://github.com/stasfilin/django-admin-global-search
